ansiscape/__init__.py
ansiscape/__main__.py
ansiscape/example.py
ansiscape/handlers.py
ansiscape/interpreter.py
ansiscape/py.typed
ansiscape/sequence.py
ansiscape/checks/__init__.py
ansiscape/checks/py.typed
ansiscape/enums/__init__.py
ansiscape/enums/blink.py
ansiscape/enums/calligraphy.py
ansiscape/enums/color_scheme.py
ansiscape/enums/font.py
ansiscape/enums/frame.py
ansiscape/enums/ideogram.py
ansiscape/enums/interpretation_key.py
ansiscape/enums/meta_color.py
ansiscape/enums/meta_interpretation.py
ansiscape/enums/named_color.py
ansiscape/enums/py.typed
ansiscape/enums/select_graphic_rendition.py
ansiscape/enums/underline.py
ansiscape/enums/weight.py
ansiscape/exceptions/__init__.py
ansiscape/exceptions/attribute.py
ansiscape/exceptions/py.typed
ansiscape/interpreters/__init__.py
ansiscape/interpreters/background.py
ansiscape/interpreters/blink.py
ansiscape/interpreters/calligraphy.py
ansiscape/interpreters/color.py
ansiscape/interpreters/conceal.py
ansiscape/interpreters/font.py
ansiscape/interpreters/foreground.py
ansiscape/interpreters/frame.py
ansiscape/interpreters/ideogram.py
ansiscape/interpreters/invert.py
ansiscape/interpreters/overline.py
ansiscape/interpreters/proportional_spacing.py
ansiscape/interpreters/py.typed
ansiscape/interpreters/strike.py
ansiscape/interpreters/underline.py
ansiscape/interpreters/weight.py
ansiscape/types/__init__.py
ansiscape/types/attributes.py
ansiscape/types/color.py
ansiscape/types/interpretation.py
ansiscape/types/interpretation_value.py
ansiscape/types/interpreter_type.py
ansiscape/types/py.typed
ansiscape/types/rgb.py
ansiscape/types/rgba.py
ansiscape/types/sequence_part.py
ansiscape/types/sequence_type.py
ansiscape/types/sequencer_result.py
ansiscape/version/VERSION
ansiscape/version/__init__.py
ansiscape/version/py.typed
ansiscape-1.1.2.dist-info/LICENSE
ansiscape-1.1.2.dist-info/METADATA
ansiscape-1.1.2.dist-info/WHEEL
ansiscape-1.1.2.dist-info/entry_points.txt
ansiscape-1.1.2.dist-info/top_level.txt
ansiscape-1.1.2.dist-info/RECORD
