Metadata-Version: 2.1
Name: ansiscape
Version: 1.1.2
Summary: Create and interpret ANSI escape codes
Home-page: https://github.com/cariad/ansiscape
Author: Cariad Eccleston
Author-email: cariad@cariad.earth
License: MIT
Classifier: Development Status :: 5 - Production/Stable
Classifier: License :: OSI Approved :: MIT License
Classifier: Natural Language :: English
Classifier: Operating System :: OS Independent
Classifier: Programming Language :: Python :: 3 :: Only
Classifier: Programming Language :: Python :: 3.10
Classifier: Programming Language :: Python :: 3.8
Classifier: Programming Language :: Python :: 3.9
Classifier: Topic :: Utilities
Classifier: Typing :: Typed
Requires-Python: >=3.8
License-File: LICENSE
